topowiz/__init__.py
topowiz/app_config.py
topowiz/http.py
topowiz/topo.py
topowiz-1.0.0.dist-info/DESCRIPTION.rst
topowiz-1.0.0.dist-info/METADATA
topowiz-1.0.0.dist-info/RECORD
topowiz-1.0.0.dist-info/WHEEL
topowiz-1.0.0.dist-info/metadata.json
topowiz-1.0.0.dist-info/top_level.txt
