Metadata-Version: 2.0
Name: topowiz
Version: 1.0.0
Summary: Wizard for creation of Romana topology files
Home-page: https://github.com/romana/topowiz
Author: Juergen Brendel
Author-email: jbrendel@romana.io
License: Apache Software License
Platform: UNKNOWN
Classifier: Programming Language :: Python
Classifier: Natural Language :: English
Classifier: Environment :: Web Environment
Classifier: Intended Audience :: System Administrators
Classifier: License :: OSI Approved :: Apache Software License
Classifier: Operating System :: POSIX :: Linux
Classifier: Topic :: System :: Networking
Requires-Dist: argparse (>=1.2.1)
Requires-Dist: ipaddr (>=2.2.0)
Requires-Dist: Flask (>=0.12.2)
Requires-Dist: WTForms (>=2.1)
Requires-Dist: Flask-WTF (>=0.14.2)
